{
	"SwordMan" : {"HP":100, "MAX_HP":100, "MP":25, "MAX_MP":25, "Stamina":50, "MAX_Stamina":50, "STR":7, "DEF":5, "MAG":2, "MR":5, "MOVE_SPEED":22.2, "ATK_SPEED":3},
	"Warrior" : {"HP":125, "MAX_HP":125, "MP":15, "MAX_MP":15, "Stamina":75, "MAX_Stamina":75, "STR":10, "DEF":7, "MAG":1, "MR":1, "MOVE_SPEED":19.0, "ATK_SPEED":2},
	"Archer" : {"HP":75, "MAX_HP":75, "MP":50, "MAX_MP":50, "Stamina":35, "MAX_Stamina":35, "STR":8, "DEF":3, "MAG":2, "MR":3, "MOVE_SPEED":24.0, "ATK_SPEED":1},
	"Witch" : {"HP":50, "MAX_HP":50, "MP":65, "MAX_MP":65, "Stamina":25, "MAX_Stamina":25, "STR":5, "DEF":1, "MAG":7, "MR":5, "MOVE_SPEED":23.0, "ATK_SPEED":4}
}










